{
  "Code": 0,
  "Message": "接口调用成功",
  "Data": {
    "pageData": [],
    "currentPage": 1398,
    "perPage": 50,
    "totalCount": 68761,
    "firstPageUrl": "https://7fenglou.com/api/v3/thread.list?perPage=50\u0026page=1",
    "nextPageUrl": "https://7fenglou.com/api/v3/thread.list?perPage=50\u0026page=1399",
    "prePageUrl": "https://7fenglou.com/api/v3/thread.list?perPage=50\u0026page=1397",
    "pageLength": 0,
    "totalPage": 1376
  },
  "RequestId": "a375b1a4-9500-4b89-b764-338c1e55d313",
  "RequestTime": "2023-07-07 23:00:54"
}